module/rpx.py
rpx_cli-0.0.9.dist-info/LICENCE
rpx_cli-0.0.9.dist-info/METADATA
rpx_cli-0.0.9.dist-info/WHEEL
rpx_cli-0.0.9.dist-info/entry_points.txt
rpx_cli-0.0.9.dist-info/top_level.txt
rpx_cli-0.0.9.dist-info/RECORD
