Metadata-Version: 2.1
Name: rpx-cli
Version: 0.0.9
Summary: CLI for react projects
Author: Lucas Patrick
License: MIT License
License-File: LICENCE
Requires-Dist: click
Requires-Dist: pathlib
